predtiler/__init__.py
predtiler/dataset.py
predtiler/tile_manager.py
predtiler/tile_stitcher.py
predtiler-0.0.2.dist-info/METADATA
predtiler-0.0.2.dist-info/WHEEL
predtiler-0.0.2.dist-info/licenses/LICENSE
predtiler-0.0.2.dist-info/RECORD
