Metadata-Version: 2.4
Name: predtiler
Version: 0.0.2
Summary: Subclassing your dataset class into a new class that can be used for tiled prediction to obtain the stitched prediction.
Project-URL: homepage, https://github.com/ashesh-0/PredTiler
Project-URL: repository, https://github.com/ashesh-0/PredTiler
Author: Ashesh
License: MIT
License-File: LICENSE
Classifier: Development Status :: 3 - Alpha
Classifier: License :: OSI Approved :: MIT License
Classifier: Programming Language :: Python :: 3
Classifier: Programming Language :: Python :: 3.9
Classifier: Programming Language :: Python :: 3.10
Classifier: Programming Language :: Python :: 3.11
Classifier: Programming Language :: Python :: 3.12
Classifier: Typing :: Typed
Requires-Python: >=3.9
Requires-Dist: numpy
Provides-Extra: dev
Requires-Dist: pre-commit; extra == 'dev'
Requires-Dist: pytest; extra == 'dev'
Requires-Dist: pytest-cov; extra == 'dev'
Requires-Dist: sybil; extra == 'dev'
Provides-Extra: examples
Requires-Dist: jupyter; extra == 'examples'
Requires-Dist: matplotlib; extra == 'examples'
